.gitignore
LICENSE
README.md
ez_setup.py
setup.py
cushion/__init__.py
cushion/api.py
cushion.egg-info/PKG-INFO
cushion.egg-info/SOURCES.txt
cushion.egg-info/dependency_links.txt
cushion.egg-info/requires.txt
cushion.egg-info/top_level.txt
cushion/tests/__init__.py
cushion/tests/test_api.py
cushion/tests/test_part.py
cushion/tests/test_read_document_request.py
cushion/tests/test_request_builder.py
cushion/tests/test_write_document_request.py