Metadata-Version: 1.0
Name: cushion
Version: 0.2
Summary: A simple wrapper for CouchDB
Home-page: http://github.com/sheysrebellion/cushion
Author: Sheheryar Sewani
Author-email: sheheryar.sewani@gmail.com
License: UNKNOWN
Platform: UNKNOWN
Classifier: Development Status :: 3 - Alpha
Classifier: Intended Audience :: Developers
Classifier: License :: OSI Approved :: MIT License
Classifier: Operating System :: OS Independent
Classifier: Topic :: Software Development :: Libraries :: Python Modules
